CHANGELOG.txt
LICENSE.txt
MANIFEST.in
README.txt
__init__.py
last_name.txt
lastname.txt
name_boy.txt
name_girl.txt
nameboy.txt
namegirl.txt
setup.py
~.pypirc.txt
data/code-city.json
shakhs/CHANGELOG.txt
shakhs/LICENSE.txt
shakhs/README.txt
shakhs/__init__.py
shakhs/codemelli.py
shakhs/last_name.txt
shakhs/lastname.txt
shakhs/name_boy.txt
shakhs/name_girl.txt
shakhs/nameboy.txt
shakhs/namegirl.txt
shakhs/setup.py
shakhs.egg-info/PKG-INFO
shakhs.egg-info/SOURCES.txt
shakhs.egg-info/dependency_links.txt
shakhs.egg-info/top_level.txt
shakhs/data/code-city.json