Metadata-Version: 2.1
Name: shakhs
Version: 0.1.6
Summary: this package generate personal details of fake iranian person
Home-page: https://pypi.org/project/shakhs/
Author: samrand majnooni
Author-email: sammajnoni@gamil.com
License: MIT
Project-URL: HomePage, https://github.com/samrand-majnooni/IR-fake-person-generator
Keywords: fake,persian,name,person,id,lastname
Platform: UNKNOWN
Classifier: Development Status :: 3 - Alpha
Classifier: Intended Audience :: Developers
Classifier: Topic :: Software Development :: Build Tools
Classifier: License :: OSI Approved :: MIT License
Classifier: Programming Language :: Python
License-File: LICENSE.txt
